odoo9_addon_stock_inventory_verification_request-9.0.1.0.0.99.dev24-py3.8-nspkg.pth
odoo_addons/stock_inventory_verification_request/README.rst
odoo_addons/stock_inventory_verification_request/__init__.py
odoo_addons/stock_inventory_verification_request/__openerp__.py
odoo_addons/stock_inventory_verification_request/data/slot_verification_request_sequence.xml
odoo_addons/stock_inventory_verification_request/i18n/am.po
odoo_addons/stock_inventory_verification_request/i18n/ar.po
odoo_addons/stock_inventory_verification_request/i18n/bg.po
odoo_addons/stock_inventory_verification_request/i18n/bs.po
odoo_addons/stock_inventory_verification_request/i18n/ca.po
odoo_addons/stock_inventory_verification_request/i18n/ca_ES.po
odoo_addons/stock_inventory_verification_request/i18n/cs.po
odoo_addons/stock_inventory_verification_request/i18n/da.po
odoo_addons/stock_inventory_verification_request/i18n/de.po
odoo_addons/stock_inventory_verification_request/i18n/el_GR.po
odoo_addons/stock_inventory_verification_request/i18n/en_GB.po
odoo_addons/stock_inventory_verification_request/i18n/es.po
odoo_addons/stock_inventory_verification_request/i18n/es_AR.po
odoo_addons/stock_inventory_verification_request/i18n/es_CL.po
odoo_addons/stock_inventory_verification_request/i18n/es_CO.po
odoo_addons/stock_inventory_verification_request/i18n/es_CR.po
odoo_addons/stock_inventory_verification_request/i18n/es_DO.po
odoo_addons/stock_inventory_verification_request/i18n/es_EC.po
odoo_addons/stock_inventory_verification_request/i18n/es_ES.po
odoo_addons/stock_inventory_verification_request/i18n/es_MX.po
odoo_addons/stock_inventory_verification_request/i18n/es_PE.po
odoo_addons/stock_inventory_verification_request/i18n/es_PY.po
odoo_addons/stock_inventory_verification_request/i18n/es_VE.po
odoo_addons/stock_inventory_verification_request/i18n/et.po
odoo_addons/stock_inventory_verification_request/i18n/eu.po
odoo_addons/stock_inventory_verification_request/i18n/fa.po
odoo9_addon_stock_inventory_verification_request-9.0.1.0.0.99.dev24.dist-info/METADATA
odoo9_addon_stock_inventory_verification_request-9.0.1.0.0.99.dev24.dist-info/WHEEL
odoo9_addon_stock_inventory_verification_request-9.0.1.0.0.99.dev24.dist-info/namespace_packages.txt
odoo9_addon_stock_inventory_verification_request-9.0.1.0.0.99.dev24.dist-info/top_level.txt
odoo9_addon_stock_inventory_verification_request-9.0.1.0.0.99.dev24.dist-info/RECORD
