Metadata-Version: 2.1
Name: odoo9-addon-stock-inventory-verification-request
Version: 9.0.1.0.0.99.dev24
Summary: Adds the capability to request a Slot Verification when a inventory is Pending to Approve
Home-page: https://github.com/OCA/stock-logistics-warehouse
Author: Eficent, Odoo Community Association (OCA)
Author-email: support@odoo-community.org
License: AGPL-3
Platform: UNKNOWN
Classifier: Programming Language :: Python
Classifier: Framework :: Odoo
Classifier: Framework :: Odoo :: 9.0
Classifier: License :: OSI Approved :: GNU Affero General Public License v3
Requires-Python: ~=2.7
Requires-Dist: odoo9-addon-stock-inventory-discrepancy
Requires-Dist: odoo (<9.1a,>=9.0a)
